datastreamservicelib/__init__.py
datastreamservicelib/compat.py
datastreamservicelib/console.py
datastreamservicelib/py.typed
datastreamservicelib/reqrep.py
datastreamservicelib/service.py
datastreamservicelib/zmqwrappers.py
datastreamservicelib-1.14.0.dist-info/LICENSE
datastreamservicelib-1.14.0.dist-info/METADATA
datastreamservicelib-1.14.0.dist-info/WHEEL
datastreamservicelib-1.14.0.dist-info/entry_points.txt
datastreamservicelib-1.14.0.dist-info/RECORD
