Metadata-Version: 2.3
Name: datastreamservicelib
Version: 1.14.0
Summary: AsyncIO eventloop helpers and Abstract Base Classes for making services that use ZMQ nice, easy and DRY
License: MIT
Author: Eero af Heurlin
Author-email: eero.afheurlin@iki.fi
Requires-Python: >=3.9,<4.0
Classifier: License :: OSI Approved :: MIT License
Classifier: Programming Language :: Python :: 3
Classifier: Programming Language :: Python :: 3.9
Classifier: Programming Language :: Python :: 3.10
Classifier: Programming Language :: Python :: 3.11
Classifier: Programming Language :: Python :: 3.12
Classifier: Programming Language :: Python :: 3.13
Requires-Dist: click (>=8.0,<9.0)
Requires-Dist: datastreamcorelib (>=1.7,<2.0)
Requires-Dist: libadvian (>=1.9,<2.0)
Requires-Dist: pyzmq (>=26.0,<27.0)
Requires-Dist: toml (>=0.10,<1.0)
Requires-Dist: tomlkit (>=0.11,<1.0)
